unsafe/__init__.py
unsafe/ext/__init__.py
unsafe/ext/bruteforce/__init__.py
unsafe/ext/bruteforce/admin_finder.py
unsafe/ext/bruteforce/cloud_passer.py
unsafe/ext/bruteforce/file_manager_finder.py
unsafe/ext/bruteforce/plugin_finder.py
unsafe/ext/cryptography/__init__.py
unsafe/ext/cryptography/decrypt.py
unsafe/ext/cryptography/encrypt.py
unsafe/ext/cryptography/hash.py
unsafe/ext/cryptography/hash_cracker.py
unsafe/ext/exploits/__init__.py
unsafe/ext/exploits/cve_2021_42013.py
unsafe/ext/exploits/cve_2024_7313.py
unsafe/ext/exploits/cve_2024_7339.py
unsafe/ext/exploits/cve_2024_7928.py
unsafe/ext/forensic/__init__.py
unsafe/ext/forensic/audio.py
unsafe/ext/forensic/images.py
unsafe/ext/forensic/pdf.py
unsafe/ext/forensic/exif/__init__.py
unsafe/ext/forensic/exif/_app1_create.py
unsafe/ext/forensic/exif/_app1_metadata.py
unsafe/ext/forensic/exif/_constants.py
unsafe/ext/forensic/exif/_datatypes.py
unsafe/ext/forensic/exif/_image.py
unsafe/ext/forensic/exif/_utils.py
unsafe/ext/forensic/exif/ifd_tag/__init__.py
unsafe/ext/forensic/exif/ifd_tag/_ascii.py
unsafe/ext/forensic/exif/ifd_tag/_base.py
unsafe/ext/forensic/exif/ifd_tag/_byte.py
unsafe/ext/forensic/exif/ifd_tag/_exifversion.py
unsafe/ext/forensic/exif/ifd_tag/_long.py
unsafe/ext/forensic/exif/ifd_tag/_rational.py
unsafe/ext/forensic/exif/ifd_tag/_short.py
unsafe/ext/forensic/exif/ifd_tag/_slong.py
unsafe/ext/forensic/exif/ifd_tag/_srational.py
unsafe/ext/forensic/exif/ifd_tag/_sshort.py
unsafe/ext/forensic/exif/ifd_tag/_user_comment.py
unsafe/ext/forensic/exif/ifd_tag/_windows_xp.py
unsafe/ext/network/__init__.py
unsafe/ext/network/lookups.py
unsafe/ext/network/proxy.py
unsafe/ext/network/scanners.py
unsafe/ext/web/__init__.py
unsafe/ext/web/crawlers.py
unsafe/ext/web/vulnerability_scanners.py
unsafe/strings/__init__.py
unsafe/strings/file_managers.py
unsafe/strings/mac_addresses.py
unsafe/strings/subdomains.py
unsafe/strings/user_agents.py
unsafe/strings/wordlist.py
unsafe/strings/wordpress.py
unsafe-1.3.dist-info/LICENSE
unsafe-1.3.dist-info/METADATA
unsafe-1.3.dist-info/WHEEL
unsafe-1.3.dist-info/top_level.txt
unsafe-1.3.dist-info/RECORD
