Metadata-Version: 2.1
Name: unsafe
Version: 1.3
Summary: A practical and optimal library for those interested in Pentest, cryptography,Vulnerability Scanner and ..
Home-page: https://github.com/ahur4/unsafe
Author: Ahura Rahmani
Author-email: ahur4.rahmani@gmail.com
License: MIT
Keywords: hack,hack-module,pentest,unsafe,osint,osint-python,hacking-python,cryptography,vulnerability-scanner,vulnerability,security,hacker,admin-finder,wordpress-scanner,instagram-osint,cve,proxy-wrapper,proxy-checker,ssh-connect,hydra,cracker,sqlmap,ahur4,mesutfd,web,acunetix
Classifier: Intended Audience :: Developers
Classifier: License :: OSI Approved :: MIT License
Classifier: Operating System :: POSIX :: Linux
Classifier: Operating System :: MacOS
Classifier: Operating System :: Microsoft :: Windows
Classifier: Programming Language :: Python :: 3.8
Classifier: Programming Language :: Python :: 3.9
Classifier: Programming Language :: Python :: 3.10
Classifier: Topic :: Security
Classifier: Topic :: Security :: Cryptography
Classifier: Topic :: Internet
Classifier: Topic :: Software Development :: Libraries
Classifier: Topic :: Software Development :: Libraries :: Python Modules
Requires-Python: >=3.8
License-File: LICENSE
Requires-Dist: beautifulsoup4 ==4.11.1
Requires-Dist: certifi ==2022.12.7
Requires-Dist: charset-normalizer ==2.1.1
Requires-Dist: idna ==3.4
Requires-Dist: mutagen ==1.46.0
Requires-Dist: Pillow ==9.3.0
Requires-Dist: plum-py ==0.8.5
Requires-Dist: PyPDF2 ==3.0.1
Requires-Dist: PySocks ==1.7.1
Requires-Dist: requests ==2.28.1
Requires-Dist: soupsieve ==2.3.2.post1
Requires-Dist: urllib3 ==1.26.13
